macdump/__init__.py
macdump/__main__.py
macdump/file.py
macdump/log.py
macdump/shared.py
macdump/system.py
macdump-1.0.1.dist-info/LICENSE.md
macdump-1.0.1.dist-info/METADATA
macdump-1.0.1.dist-info/WHEEL
macdump-1.0.1.dist-info/entry_points.txt
macdump-1.0.1.dist-info/top_level.txt
macdump-1.0.1.dist-info/RECORD
