Metadata-Version: 2.1
Name: macdump
Version: 1.0.1
Summary: Dump macOS 1.8+ system user hashes
Author-email: Dominic Breuker <admin@dominicbreuker.com>
Project-URL: Homepage, https://github.com/dominicbreuker/macdump
Keywords: hashcat,macos,hashdump
Classifier: License :: OSI Approved :: MIT License
Classifier: Programming Language :: Python
Classifier: Programming Language :: Python :: 3
Requires-Python: >=3.9
License-File: LICENSE.md
Provides-Extra: dev
Requires-Dist: black ; extra == 'dev'
Requires-Dist: bumpver ; extra == 'dev'
Requires-Dist: pytest ; extra == 'dev'
